cpp_module/__init__.py
cpp_module/cpp_extension.cp314t-win_amd64.pyd
cpp_module/cpp_extension.cpp
example_cpp-0.1.1.dist-info/METADATA
example_cpp-0.1.1.dist-info/WHEEL
example_cpp-0.1.1.dist-info/top_level.txt
example_cpp-0.1.1.dist-info/RECORD
