Metadata-Version: 2.4
Name: example-cpp
Version: 0.1.1
Summary: Add your description here
Author: RL
Author-email: your.email@example.com
Requires-Python: >=3.14
Requires-Dist: pybind11>=3.0.1
Requires-Dist: pytest>=9.0.1
Requires-Dist: setuptools>=80.9.0
Dynamic: author
Dynamic: author-email
Dynamic: requires-python
